{
  "RuleName": "Autowaiver Makeblock.xToolStudio ",
  "Schedule": "Hourly",
  "Conditions": [
    {
      "Key": "PackageIdentifier",
      "Comparison": "Equals",
      "Value": "Makeblock.xToolStudio"
    },
    {
      "Key": "Labels",
      "Comparison": "Match",
      "Value": "Validation-Domain"
    },
    {
      "Key": "InstallerUrl",
      "Comparison": "Equals",
      "Value": "storage.atomm.com"
    }
  ],
  "Actions": [
    {
      "Action": "ReplyToPR",
      "Data": "@wingetbot waivers Add Validation-Domain"
    }
  ]
}
